meteofrance_api/__init__.py
meteofrance_api/__main__.py
meteofrance_api/client.py
meteofrance_api/const.py
meteofrance_api/exceptions.py
meteofrance_api/helpers.py
meteofrance_api/model/__init__.py
meteofrance_api/model/dictionary.py
meteofrance_api/model/forecast.py
meteofrance_api/model/observation.py
meteofrance_api/model/picture_of_the_day.py
meteofrance_api/model/place.py
meteofrance_api/model/rain.py
meteofrance_api/model/warning.py
meteofrance_api/py.typed
meteofrance_api/session.py
meteofrance_api-1.4.0.dist-info/LICENSE.rst
meteofrance_api-1.4.0.dist-info/METADATA
meteofrance_api-1.4.0.dist-info/WHEEL
meteofrance_api-1.4.0.dist-info/entry_points.txt
meteofrance_api-1.4.0.dist-info/RECORD
