Metadata-Version: 2.1
Name: meteofrance-api
Version: 1.4.0
Summary: Python client for Météo-France API.
Home-page: https://github.com/hacf-fr/meteofrance-api
License: MIT
Keywords: weather,weather-api,meteo
Author: oncleben31
Author-email: oncleben31@gmail.com
Requires-Python: >=3.8.18,<4.0.0
Classifier: Development Status :: 5 - Production/Stable
Classifier: License :: OSI Approved :: MIT License
Classifier: Operating System :: OS Independent
Classifier: Programming Language :: Python :: 3
Classifier: Programming Language :: Python :: 3.9
Classifier: Programming Language :: Python :: 3.10
Classifier: Programming Language :: Python :: 3.11
Classifier: Programming Language :: Python :: 3.12
Classifier: Programming Language :: Python :: 3.13
Classifier: Programming Language :: Python :: 3.8
Requires-Dist: pytz (>=2024.1)
Requires-Dist: requests (>=2.32.3,<3.0.0)
Requires-Dist: typing-extensions (>=3.8.18,<5.0.0) ; python_version >= "3.8" and python_version < "3.12"
Project-URL: Changelog, https://github.com/hacf-fr/meteofrance-api/releases
Project-URL: Documentation, https://meteofrance-api.readthedocs.io
Project-URL: Repository, https://github.com/hacf-fr/meteofrance-api
